bg3modutils/__init__.py
bg3modutils/model/__init__.py
bg3modutils/model/action_resource.py
bg3modutils/model/interrupt.py
bg3modutils/model/meta.py
bg3modutils/model/mod.py
bg3modutils/model/passive.py
bg3modutils/model/progression.py
bg3modutils/model/shout.py
bg3modutils/model/spell.py
bg3modutils/utils/__init__.py
bg3modutils/utils/debug.py
bg3modutils/utils/enums.py
bg3modutils/utils/file_manager.py
bg3modutils/utils/lslib.py
bg3modutils/utils/paths.py
bg3modutils/utils/ExportTool/AlphaFS.dll
bg3modutils/utils/ExportTool/ConverterApp.exe
bg3modutils/utils/ExportTool/ConverterApp.exe.config
bg3modutils/utils/ExportTool/LSLib.dll
bg3modutils/utils/ExportTool/LSLibNative.dll
bg3modutils/utils/ExportTool/LZ4.dll
bg3modutils/utils/ExportTool/Newtonsoft.Json.dll
bg3modutils/utils/ExportTool/OpenTK.dll
bg3modutils/utils/ExportTool/QUT.ShiftReduceParser.dll
bg3modutils/utils/ExportTool/granny2.dll
bg3modutils/utils/ExportTool/settings.json
bg3modutils/utils/ExportTool/zlib.net.dll
bg3modutils/utils/ExportTool/Tools/AlphaFS.dll
bg3modutils/utils/ExportTool/Tools/CommandLineArgumentsParser.dll
bg3modutils/utils/ExportTool/Tools/DebuggerFrontend.exe
bg3modutils/utils/ExportTool/Tools/DebuggerFrontend.exe.config
bg3modutils/utils/ExportTool/Tools/Google.Protobuf.dll
bg3modutils/utils/ExportTool/Tools/LSLib.dll
bg3modutils/utils/ExportTool/Tools/LSLibNative.dll
bg3modutils/utils/ExportTool/Tools/LZ4.dll
bg3modutils/utils/ExportTool/Tools/Newtonsoft.Json.dll
bg3modutils/utils/ExportTool/Tools/OpenTK.dll
bg3modutils/utils/ExportTool/Tools/QUT.ShiftReduceParser.dll
bg3modutils/utils/ExportTool/Tools/RconClient.exe
bg3modutils/utils/ExportTool/Tools/RconClient.exe.config
bg3modutils/utils/ExportTool/Tools/StatParser.exe
bg3modutils/utils/ExportTool/Tools/StatParser.exe.config
bg3modutils/utils/ExportTool/Tools/StoryCompiler.exe
bg3modutils/utils/ExportTool/Tools/StoryCompiler.exe.config
bg3modutils/utils/ExportTool/Tools/StoryDecompiler.exe
bg3modutils-0.0.14.dist-info/METADATA
bg3modutils-0.0.14.dist-info/WHEEL
bg3modutils-0.0.14.dist-info/licenses/LICENCE
bg3modutils-0.0.14.dist-info/RECORD
